filtrark/__init__.py
filtrark/api.py
filtrark/expression_parser.py
filtrark/safe_eval.py
filtrark/sql_parser.py
filtrark/types.py
filtrark-0.10.0.dist-info/LICENSE
filtrark-0.10.0.dist-info/WHEEL
filtrark-0.10.0.dist-info/METADATA
filtrark-0.10.0.dist-info/RECORD
