Metadata-Version: 2.1
Name: filtrark
Version: 0.10.0
Summary: Build filter clauses from instruction lists
License: MIT
Author: Knowark
Requires-Python: >=3.8,<4.0
Classifier: License :: OSI Approved :: MIT License
Classifier: Programming Language :: Python :: 3
Classifier: Programming Language :: Python :: 3.8
Classifier: Programming Language :: Python :: 3.9
